CHANGELOG.txt
LICENCE.txt
MANIFEST.in
README.txt
setup.py
palbasiccalculator/__init__.py
palbasiccalculator.egg-info/PKG-INFO
palbasiccalculator.egg-info/SOURCES.txt
palbasiccalculator.egg-info/dependency_links.txt
palbasiccalculator.egg-info/top_level.txt