Metadata-Version: 2.1
Name: palbasiccalculator
Version: 0.0.1
Summary: A very basic calculator
Home-page: 
Author: Pallavi Moulick
Author-email: pmoulick21@gmail.com
License: MIT
Keywords: calculator
Classifier: Development Status :: 5 - Production/Stable
Classifier: Intended Audience :: Education
Classifier: Operating System :: OS Independent
Classifier: License :: OSI Approved :: MIT License
Classifier: Programming Language :: Python :: 3.11
License-File: LICENCE.txt
